spotigrabber/spotigrabber.py
spotigrabber-0.1.0.dist-info/LICENSE.txt
spotigrabber-0.1.0.dist-info/METADATA
spotigrabber-0.1.0.dist-info/WHEEL
spotigrabber-0.1.0.dist-info/top_level.txt
spotigrabber-0.1.0.dist-info/RECORD
