Metadata-Version: 2.1
Name: spotigrabber
Version: 0.1.0
Summary: Grabber your spotify playlists and recently played songs.
Author-email: bebissig <bebissig@gmail.com>
Project-URL: Homepage, https://github.com/bebissig/spotify_grab_current_playlists
Classifier: Programming Language :: Python :: 3
Classifier: License :: OSI Approved :: MIT License
Classifier: Operating System :: OS Independent
Requires-Python: >=3.7
License-File: LICENSE.txt
Requires-Dist: async-timeout
Requires-Dist: certifi
Requires-Dist: charset-normalizer
Requires-Dist: et-xmlfile
Requires-Dist: idna
Requires-Dist: importlib-metadata
Requires-Dist: numpy
Requires-Dist: openpyxl
Requires-Dist: pandas
Requires-Dist: python-dateutil
Requires-Dist: pytz
Requires-Dist: redis
Requires-Dist: requests
Requires-Dist: six
Requires-Dist: spotipy
Requires-Dist: typing-extensions
Requires-Dist: urllib3
Requires-Dist: zipp
